CHANGES.txt
DEPENDENCES.txt
README.txt
setup.py
src/__init__.py
src/pd/__init__.py
src/pd.imalyzer.egg-info/PKG-INFO
src/pd.imalyzer.egg-info/SOURCES.txt
src/pd.imalyzer.egg-info/dependency_links.txt
src/pd.imalyzer.egg-info/entry_points.txt
src/pd.imalyzer.egg-info/namespace_packages.txt
src/pd.imalyzer.egg-info/requires.txt
src/pd.imalyzer.egg-info/top_level.txt
src/pd.imalyzer.egg-info/zip-safe
src/pd/imalyzer/__init__.py
src/pd/imalyzer/cluster.py
src/pd/imalyzer/featurehideadapter.py
src/pd/imalyzer/imalyzer.py
src/pd/imalyzer/interfaces.py
src/pd/imalyzer/kernel.py
src/pd/imalyzer/libimalyzer.py
src/pd/imalyzer/orphan.py
src/pd/imalyzer/pd.imalyzer.txt
src/pd/imalyzer/suborphan.py
src/pd/imalyzer/subsetadapter.py
src/pd/imalyzer/subtree.py
src/pd/imalyzer/subtrees.py
src/pd/imalyzer/subtrees_div.py
