Metadata-Version: 1.0
Name: pd.imalyzer
Version: 0.0.4
Summary: Library for dependences analys
Home-page: http://www.dreambot.ru/product/DreamBotOtherReleases/pd.imalyzer
Author: Andrey Orlov
Author-email: dbdt@dreambot.ru
License: GPL v2.1
Platform: UNKNOWN
Classifier: Intended Audience :: Developers
Classifier: License :: OSI Approved :: GNU General Public License (GPL)
Classifier: Programming Language :: Python
Classifier: Operating System :: OS Independent
